bitsharesscripts/__init__.py
bitsharesscripts/decorators.py
bitsharesscripts/functions.py
bitsharesscripts-3.1.0.dist-info/LICENSE.md
bitsharesscripts-3.1.0.dist-info/WHEEL
bitsharesscripts-3.1.0.dist-info/METADATA
bitsharesscripts-3.1.0.dist-info/RECORD
