Metadata-Version: 2.1
Name: bitsharesscripts
Version: 3.1.0
Summary: A set of scripts for BitShares
Home-page: https://github.com/bitfag/bitshares-scripts
License: MIT
Author: Vladimir Kamarzin
Author-email: vvk@vvk.pp.ru
Requires-Python: >=3.6.1,<4.0.0
Classifier: License :: OSI Approved :: MIT License
Classifier: Programming Language :: Python :: 3
Classifier: Programming Language :: Python :: 3.7
Classifier: Programming Language :: Python :: 3.8
Classifier: Programming Language :: Python :: 3.9
Requires-Dist: bitshares (>=0.5.0,<0.6.0)
Requires-Dist: click (>=7.1.1,<8.0.0)
Requires-Dist: uptick (>=0.2.4,<0.3.0)
Project-URL: Repository, https://github.com/bitfag/bitshares-scripts
